Verilog/half_adder.v
`timescale 1ns/1ps
module half_adder (
    a,b,sum,carry
);

  input wire a,b;
  output wire sum,carry;

  xor x1(sum,a,b);
  and x2(carry,a,b);
    
endmodule

Verilog/full_adder.v
`timescale 1ns/1ps
`include "half_adder.v"

module full_adder (
    inp_a,inp_b,inp_cin,out_sum,out_carry
);

input  inp_a,inp_b,inp_cin;
output  out_sum,out_carry;
wire sum_1,carry_1,carry_2;

half_adder h1(inp_a,inp_b,sum_1,carry_1);
half_adder h2(inp_cin,carry_1,out_sum,carry_2);
or h3(out_carry,carry_1,carry_2);

    
endmodule

Verilog/full_adder_tb.v
`timescale 1ns/1ps
`include "full_adder.v"

module full_adder_tb;
  initial begin
      $dumpfile("full_adder_test.vcd");
      $dumpvars(0,full_adder_tb);
  end
    
  reg A,B,C;
  wire SUM,CARRY;

  full_adder h1(
      .inp_a(A),
      .inp_b(B),
      .inp_cin(C),
      .out_sum(SUM),
      .out_carry(CARRY)
      );

      initial begin
          A=1'b0;
          B=1'b0;
          C=1'b0;
          #5;

          A=1'b1;
          B=1'b0;
          C=1'b0;
          #5;

          A=1'b0;
          B=1'b1;
          C=1'b0;
          #5;

          A=1'b1;
          B=1'b1;
          C=1'b0;
          #5;

          A=1'b0;
          B=1'b0;
          C=1'b1;
          #5;

          A=1'b1;
          B=1'b0;
          C=1'b1;
          #5;

          A=1'b0;
          B=1'b1;
          C=1'b1;
          #5;

          A=1'b1;
          B=1'b1;
          C=1'b1;
          #5;
      end

endmodule

Verilog/full_adder_test.vcd
$date
	Wed May  5 01:17:48 2021
$end
$version
	Icarus Verilog
$end
$timescale
	1ps
$end
$scope module full_adder_tb $end
$var wire 1 ! SUM $end
$var wire 1 " CARRY $end
$var reg 1 # A $end
$var reg 1 $ B $end
$var reg 1 % C $end
$scope module h1 $end
$var wire 1 # inp_a $end
$var wire 1 $ inp_b $end
$var wire 1 % inp_cin $end
$var wire 1 " out_carry $end
$var wire 1 & sum_1 $end
$var wire 1 ! out_sum $end
$var wire 1 ' carry_2 $end
$var wire 1 ( carry_1 $end
$scope module h1 $end
$var wire 1 # a $end
$var wire 1 $ b $end
$var wire 1 ( carry $end
$var wire 1 & sum $end
$upscope $end
$scope module h2 $end
$var wire 1 % a $end
$var wire 1 ( b $end
$var wire 1 ' carry $end
$var wire 1 ! sum $end
$upscope $end
$upscope $end
$upscope $end
$enddefinitions $end
#0
$dumpvars
0(
0'
0&
0%
0$
0#
0"
0!
$end
#5000
1&
1#
#10000
1$
0#
#15000
1!
1"
0&
1(
1#
#20000
0"
0(
1%
0$
0#
#25000
1&
1#
#30000
1$
0#
#35000
0!
1'
1"
0&
1(
1#
